__init__.py
retcode.py
setup.py
utils.py
moyu.egg-info/PKG-INFO
moyu.egg-info/SOURCES.txt
moyu.egg-info/dependency_links.txt
moyu.egg-info/requires.txt
moyu.egg-info/top_level.txt